{
  "start": "2023-11-04",
  "end": "2024-11-02",
  "package": "escape-string-applescript",
  "downloads": [
    {
      "downloads": 6703,
      "day": "2023-11-04"
    },
    {
      "downloads": 7092,
      "day": "2023-11-05"
    },
    {
      "downloads": 26446,
      "day": "2023-11-06"
    },
    {
      "downloads": 28540,
      "day": "2023-11-07"
    },
    {
      "downloads": 27561,
      "day": "2023-11-08"
    },
    {
      "downloads": 29237,
      "day": "2023-11-09"
    },
    {
      "downloads": 25152,
      "day": "2023-11-10"
    },
    {
      "downloads": 6499,
      "day": "2023-11-11"
    },
    {
      "downloads": 6972,
      "day": "2023-11-12"
    },
    {
      "downloads": 29890,
      "day": "2023-11-13"
    },
    {
      "downloads": 30699,
      "day": "2023-11-14"
    },
    {
      "downloads": 30393,
      "day": "2023-11-15"
    },
    {
      "downloads": 32136,
      "day": "2023-11-16"
    },
    {
      "downloads": 28968,
      "day": "2023-11-17"
    },
    {
      "downloads": 7424,
      "day": "2023-11-18"
    },
    {
      "downloads": 7453,
      "day": "2023-11-19"
    },
    {
      "downloads": 28567,
      "day": "2023-11-20"
    },
    {
      "downloads": 30928,
      "day": "2023-11-21"
    },
    {
      "downloads": 29302,
      "day": "2023-11-22"
    },
    {
      "downloads": 24484,
      "day": "2023-11-23"
    },
    {
      "downloads": 20619,
      "day": "2023-11-24"
    },
    {
      "downloads": 6485,
      "day": "2023-11-25"
    },
    {
      "downloads": 6886,
      "day": "2023-11-26"
    },
    {
      "downloads": 26981,
      "day": "2023-11-27"
    },
    {
      "downloads": 29447,
      "day": "2023-11-28"
    },
    {
      "downloads": 30088,
      "day": "2023-11-29"
    },
    {
      "downloads": 29219,
      "day": "2023-11-30"
    },
    {
      "downloads": 27662,
      "day": "2023-12-01"
    },
    {
      "downloads": 8120,
      "day": "2023-12-02"
    },
    {
      "downloads": 6830,
      "day": "2023-12-03"
    },
    {
      "downloads": 29238,
      "day": "2023-12-04"
    },
    {
      "downloads": 29505,
      "day": "2023-12-05"
    },
    {
      "downloads": 30634,
      "day": "2023-12-06"
    },
    {
      "downloads": 32915,
      "day": "2023-12-07"
    },
    {
      "downloads": 27685,
      "day": "2023-12-08"
    },
    {
      "downloads": 10235,
      "day": "2023-12-09"
    },
    {
      "downloads": 10623,
      "day": "2023-12-10"
    },
    {
      "downloads": 33311,
      "day": "2023-12-11"
    },
    {
      "downloads": 33443,
      "day": "2023-12-12"
    },
    {
      "downloads": 28547,
      "day": "2023-12-13"
    },
    {
      "downloads": 28951,
      "day": "2023-12-14"
    },
    {
      "downloads": 25848,
      "day": "2023-12-15"
    },
    {
      "downloads": 7348,
      "day": "2023-12-16"
    },
    {
      "downloads": 7458,
      "day": "2023-12-17"
    },
    {
      "downloads": 29460,
      "day": "2023-12-18"
    },
    {
      "downloads": 29909,
      "day": "2023-12-19"
    },
    {
      "downloads": 29728,
      "day": "2023-12-20"
    },
    {
      "downloads": 25389,
      "day": "2023-12-21"
    },
    {
      "downloads": 20377,
      "day": "2023-12-22"
    },
    {
      "downloads": 6496,
      "day": "2023-12-23"
    },
    {
      "downloads": 6135,
      "day": "2023-12-24"
    },
    {
      "downloads": 9339,
      "day": "2023-12-25"
    },
    {
      "downloads": 16668,
      "day": "2023-12-26"
    },
    {
      "downloads": 19270,
      "day": "2023-12-27"
    },
    {
      "downloads": 19874,
      "day": "2023-12-28"
    },
    {
      "downloads": 16062,
      "day": "2023-12-29"
    },
    {
      "downloads": 6070,
      "day": "2023-12-30"
    },
    {
      "downloads": 5842,
      "day": "2023-12-31"
    },
    {
      "downloads": 7955,
      "day": "2024-01-01"
    },
    {
      "downloads": 22588,
      "day": "2024-01-02"
    },
    {
      "downloads": 26879,
      "day": "2024-01-03"
    },
    {
      "downloads": 28536,
      "day": "2024-01-04"
    },
    {
      "downloads": 24297,
      "day": "2024-01-05"
    },
    {
      "downloads": 7630,
      "day": "2024-01-06"
    },
    {
      "downloads": 7117,
      "day": "2024-01-07"
    },
    {
      "downloads": 30115,
      "day": "2024-01-08"
    },
    {
      "downloads": 33850,
      "day": "2024-01-09"
    },
    {
      "downloads": 32044,
      "day": "2024-01-10"
    },
    {
      "downloads": 32356,
      "day": "2024-01-11"
    },
    {
      "downloads": 30066,
      "day": "2024-01-12"
    },
    {
      "downloads": 8724,
      "day": "2024-01-13"
    },
    {
      "downloads": 9222,
      "day": "2024-01-14"
    },
    {
      "downloads": 30129,
      "day": "2024-01-15"
    },
    {
      "downloads": 34372,
      "day": "2024-01-16"
    },
    {
      "downloads": 34117,
      "day": "2024-01-17"
    },
    {
      "downloads": 32447,
      "day": "2024-01-18"
    },
    {
      "downloads": 31381,
      "day": "2024-01-19"
    },
    {
      "downloads": 9135,
      "day": "2024-01-20"
    },
    {
      "downloads": 8731,
      "day": "2024-01-21"
    },
    {
      "downloads": 35943,
      "day": "2024-01-22"
    },
    {
      "downloads": 34719,
      "day": "2024-01-23"
    },
    {
      "downloads": 36046,
      "day": "2024-01-24"
    },
    {
      "downloads": 32079,
      "day": "2024-01-25"
    },
    {
      "downloads": 29077,
      "day": "2024-01-26"
    },
    {
      "downloads": 8536,
      "day": "2024-01-27"
    },
    {
      "downloads": 8198,
      "day": "2024-01-28"
    },
    {
      "downloads": 36354,
      "day": "2024-01-29"
    },
    {
      "downloads": 38525,
      "day": "2024-01-30"
    },
    {
      "downloads": 34795,
      "day": "2024-01-31"
    },
    {
      "downloads": 39143,
      "day": "2024-02-01"
    },
    {
      "downloads": 31888,
      "day": "2024-02-02"
    },
    {
      "downloads": 7793,
      "day": "2024-02-03"
    },
    {
      "downloads": 9113,
      "day": "2024-02-04"
    },
    {
      "downloads": 37370,
      "day": "2024-02-05"
    },
    {
      "downloads": 40107,
      "day": "2024-02-06"
    },
    {
      "downloads": 38221,
      "day": "2024-02-07"
    },
    {
      "downloads": 35699,
      "day": "2024-02-08"
    },
    {
      "downloads": 31740,
      "day": "2024-02-09"
    },
    {
      "downloads": 9596,
      "day": "2024-02-10"
    },
    {
      "downloads": 8602,
      "day": "2024-02-11"
    },
    {
      "downloads": 35567,
      "day": "2024-02-12"
    },
    {
      "downloads": 34223,
      "day": "2024-02-13"
    },
    {
      "downloads": 34259,
      "day": "2024-02-14"
    },
    {
      "downloads": 38000,
      "day": "2024-02-15"
    },
    {
      "downloads": 33714,
      "day": "2024-02-16"
    },
    {
      "downloads": 9107,
      "day": "2024-02-17"
    },
    {
      "downloads": 9059,
      "day": "2024-02-18"
    },
    {
      "downloads": 32240,
      "day": "2024-02-19"
    },
    {
      "downloads": 38285,
      "day": "2024-02-20"
    },
    {
      "downloads": 40153,
      "day": "2024-02-21"
    },
    {
      "downloads": 39075,
      "day": "2024-02-22"
    },
    {
      "downloads": 34213,
      "day": "2024-02-23"
    },
    {
      "downloads": 8907,
      "day": "2024-02-24"
    },
    {
      "downloads": 9946,
      "day": "2024-02-25"
    },
    {
      "downloads": 39064,
      "day": "2024-02-26"
    },
    {
      "downloads": 41630,
      "day": "2024-02-27"
    },
    {
      "downloads": 37931,
      "day": "2024-02-28"
    },
    {
      "downloads": 39657,
      "day": "2024-02-29"
    },
    {
      "downloads": 34689,
      "day": "2024-03-01"
    },
    {
      "downloads": 9863,
      "day": "2024-03-02"
    },
    {
      "downloads": 8221,
      "day": "2024-03-03"
    },
    {
      "downloads": 39480,
      "day": "2024-03-04"
    },
    {
      "downloads": 44375,
      "day": "2024-03-05"
    },
    {
      "downloads": 40364,
      "day": "2024-03-06"
    },
    {
      "downloads": 44157,
      "day": "2024-03-07"
    },
    {
      "downloads": 34199,
      "day": "2024-03-08"
    },
    {
      "downloads": 9741,
      "day": "2024-03-09"
    },
    {
      "downloads": 9533,
      "day": "2024-03-10"
    },
    {
      "downloads": 38664,
      "day": "2024-03-11"
    },
    {
      "downloads": 42158,
      "day": "2024-03-12"
    },
    {
      "downloads": 44446,
      "day": "2024-03-13"
    },
    {
      "downloads": 40534,
      "day": "2024-03-14"
    },
    {
      "downloads": 38196,
      "day": "2024-03-15"
    },
    {
      "downloads": 9526,
      "day": "2024-03-16"
    },
    {
      "downloads": 9023,
      "day": "2024-03-17"
    },
    {
      "downloads": 40067,
      "day": "2024-03-18"
    },
    {
      "downloads": 41958,
      "day": "2024-03-19"
    },
    {
      "downloads": 41744,
      "day": "2024-03-20"
    },
    {
      "downloads": 43195,
      "day": "2024-03-21"
    },
    {
      "downloads": 34255,
      "day": "2024-03-22"
    },
    {
      "downloads": 9422,
      "day": "2024-03-23"
    },
    {
      "downloads": 9708,
      "day": "2024-03-24"
    },
    {
      "downloads": 42146,
      "day": "2024-03-25"
    },
    {
      "downloads": 29698,
      "day": "2024-03-26"
    },
    {
      "downloads": 42061,
      "day": "2024-03-27"
    },
    {
      "downloads": 38304,
      "day": "2024-03-28"
    },
    {
      "downloads": 26637,
      "day": "2024-03-29"
    },
    {
      "downloads": 7735,
      "day": "2024-03-30"
    },
    {
      "downloads": 7449,
      "day": "2024-03-31"
    },
    {
      "downloads": 31592,
      "day": "2024-04-01"
    },
    {
      "downloads": 41776,
      "day": "2024-04-02"
    },
    {
      "downloads": 40334,
      "day": "2024-04-03"
    },
    {
      "downloads": 37837,
      "day": "2024-04-04"
    },
    {
      "downloads": 32215,
      "day": "2024-04-05"
    },
    {
      "downloads": 7843,
      "day": "2024-04-06"
    },
    {
      "downloads": 8086,
      "day": "2024-04-07"
    },
    {
      "downloads": 39200,
      "day": "2024-04-08"
    },
    {
      "downloads": 38942,
      "day": "2024-04-09"
    },
    {
      "downloads": 39962,
      "day": "2024-04-10"
    },
    {
      "downloads": 43075,
      "day": "2024-04-11"
    },
    {
      "downloads": 36354,
      "day": "2024-04-12"
    },
    {
      "downloads": 8934,
      "day": "2024-04-13"
    },
    {
      "downloads": 7634,
      "day": "2024-04-14"
    },
    {
      "downloads": 41756,
      "day": "2024-04-15"
    },
    {
      "downloads": 40537,
      "day": "2024-04-16"
    },
    {
      "downloads": 42663,
      "day": "2024-04-17"
    },
    {
      "downloads": 35695,
      "day": "2024-04-18"
    },
    {
      "downloads": 37576,
      "day": "2024-04-19"
    },
    {
      "downloads": 7516,
      "day": "2024-04-20"
    },
    {
      "downloads": 8088,
      "day": "2024-04-21"
    },
    {
      "downloads": 41166,
      "day": "2024-04-22"
    },
    {
      "downloads": 40366,
      "day": "2024-04-23"
    },
    {
      "downloads": 41160,
      "day": "2024-04-24"
    },
    {
      "downloads": 43543,
      "day": "2024-04-25"
    },
    {
      "downloads": 36054,
      "day": "2024-04-26"
    },
    {
      "downloads": 11564,
      "day": "2024-04-27"
    },
    {
      "downloads": 10274,
      "day": "2024-04-28"
    },
    {
      "downloads": 40751,
      "day": "2024-04-29"
    },
    {
      "downloads": 42720,
      "day": "2024-04-30"
    },
    {
      "downloads": 28322,
      "day": "2024-05-01"
    },
    {
      "downloads": 46170,
      "day": "2024-05-02"
    },
    {
      "downloads": 36601,
      "day": "2024-05-03"
    },
    {
      "downloads": 11050,
      "day": "2024-05-04"
    },
    {
      "downloads": 10208,
      "day": "2024-05-05"
    },
    {
      "downloads": 35603,
      "day": "2024-05-06"
    },
    {
      "downloads": 40042,
      "day": "2024-05-07"
    },
    {
      "downloads": 38051,
      "day": "2024-05-08"
    },
    {
      "downloads": 38161,
      "day": "2024-05-09"
    },
    {
      "downloads": 33145,
      "day": "2024-05-10"
    },
    {
      "downloads": 10847,
      "day": "2024-05-11"
    },
    {
      "downloads": 9545,
      "day": "2024-05-12"
    },
    {
      "downloads": 42328,
      "day": "2024-05-13"
    },
    {
      "downloads": 43912,
      "day": "2024-05-14"
    },
    {
      "downloads": 45295,
      "day": "2024-05-15"
    },
    {
      "downloads": 45699,
      "day": "2024-05-16"
    },
    {
      "downloads": 37537,
      "day": "2024-05-17"
    },
    {
      "downloads": 9325,
      "day": "2024-05-18"
    },
    {
      "downloads": 9902,
      "day": "2024-05-19"
    },
    {
      "downloads": 33552,
      "day": "2024-05-20"
    },
    {
      "downloads": 44272,
      "day": "2024-05-21"
    },
    {
      "downloads": 43700,
      "day": "2024-05-22"
    },
    {
      "downloads": 44131,
      "day": "2024-05-23"
    },
    {
      "downloads": 38319,
      "day": "2024-05-24"
    },
    {
      "downloads": 8498,
      "day": "2024-05-25"
    },
    {
      "downloads": 9207,
      "day": "2024-05-26"
    },
    {
      "downloads": 33587,
      "day": "2024-05-27"
    },
    {
      "downloads": 41970,
      "day": "2024-05-28"
    },
    {
      "downloads": 49657,
      "day": "2024-05-29"
    },
    {
      "downloads": 43102,
      "day": "2024-05-30"
    },
    {
      "downloads": 38778,
      "day": "2024-05-31"
    },
    {
      "downloads": 11109,
      "day": "2024-06-01"
    },
    {
      "downloads": 10252,
      "day": "2024-06-02"
    },
    {
      "downloads": 44415,
      "day": "2024-06-03"
    },
    {
      "downloads": 43168,
      "day": "2024-06-04"
    },
    {
      "downloads": 48250,
      "day": "2024-06-05"
    },
    {
      "downloads": 46651,
      "day": "2024-06-06"
    },
    {
      "downloads": 37392,
      "day": "2024-06-07"
    },
    {
      "downloads": 8654,
      "day": "2024-06-08"
    },
    {
      "downloads": 9582,
      "day": "2024-06-09"
    },
    {
      "downloads": 40714,
      "day": "2024-06-10"
    },
    {
      "downloads": 46170,
      "day": "2024-06-11"
    },
    {
      "downloads": 46538,
      "day": "2024-06-12"
    },
    {
      "downloads": 48699,
      "day": "2024-06-13"
    },
    {
      "downloads": 41857,
      "day": "2024-06-14"
    },
    {
      "downloads": 10013,
      "day": "2024-06-15"
    },
    {
      "downloads": 10214,
      "day": "2024-06-16"
    },
    {
      "downloads": 45419,
      "day": "2024-06-17"
    },
    {
      "downloads": 51652,
      "day": "2024-06-18"
    },
    {
      "downloads": 47077,
      "day": "2024-06-19"
    },
    {
      "downloads": 44991,
      "day": "2024-06-20"
    },
    {
      "downloads": 39394,
      "day": "2024-06-21"
    },
    {
      "downloads": 9068,
      "day": "2024-06-22"
    },
    {
      "downloads": 9121,
      "day": "2024-06-23"
    },
    {
      "downloads": 44747,
      "day": "2024-06-24"
    },
    {
      "downloads": 46218,
      "day": "2024-06-25"
    },
    {
      "downloads": 45726,
      "day": "2024-06-26"
    },
    {
      "downloads": 49611,
      "day": "2024-06-27"
    },
    {
      "downloads": 46944,
      "day": "2024-06-28"
    },
    {
      "downloads": 11561,
      "day": "2024-06-29"
    },
    {
      "downloads": 9447,
      "day": "2024-06-30"
    },
    {
      "downloads": 49460,
      "day": "2024-07-01"
    },
    {
      "downloads": 55865,
      "day": "2024-07-02"
    },
    {
      "downloads": 50676,
      "day": "2024-07-03"
    },
    {
      "downloads": 39430,
      "day": "2024-07-04"
    },
    {
      "downloads": 32942,
      "day": "2024-07-05"
    },
    {
      "downloads": 10279,
      "day": "2024-07-06"
    },
    {
      "downloads": 10749,
      "day": "2024-07-07"
    },
    {
      "downloads": 50116,
      "day": "2024-07-08"
    },
    {
      "downloads": 51623,
      "day": "2024-07-09"
    },
    {
      "downloads": 47922,
      "day": "2024-07-10"
    },
    {
      "downloads": 51066,
      "day": "2024-07-11"
    },
    {
      "downloads": 42834,
      "day": "2024-07-12"
    },
    {
      "downloads": 10307,
      "day": "2024-07-13"
    },
    {
      "downloads": 11288,
      "day": "2024-07-14"
    },
    {
      "downloads": 47056,
      "day": "2024-07-15"
    },
    {
      "downloads": 49765,
      "day": "2024-07-16"
    },
    {
      "downloads": 51063,
      "day": "2024-07-17"
    },
    {
      "downloads": 47065,
      "day": "2024-07-18"
    },
    {
      "downloads": 44806,
      "day": "2024-07-19"
    },
    {
      "downloads": 10597,
      "day": "2024-07-20"
    },
    {
      "downloads": 11314,
      "day": "2024-07-21"
    },
    {
      "downloads": 49696,
      "day": "2024-07-22"
    },
    {
      "downloads": 52738,
      "day": "2024-07-23"
    },
    {
      "downloads": 51960,
      "day": "2024-07-24"
    },
    {
      "downloads": 50307,
      "day": "2024-07-25"
    },
    {
      "downloads": 42872,
      "day": "2024-07-26"
    },
    {
      "downloads": 9062,
      "day": "2024-07-27"
    },
    {
      "downloads": 10293,
      "day": "2024-07-28"
    },
    {
      "downloads": 44782,
      "day": "2024-07-29"
    },
    {
      "downloads": 49363,
      "day": "2024-07-30"
    },
    {
      "downloads": 50634,
      "day": "2024-07-31"
    },
    {
      "downloads": 46479,
      "day": "2024-08-01"
    },
    {
      "downloads": 39675,
      "day": "2024-08-02"
    },
    {
      "downloads": 9548,
      "day": "2024-08-03"
    },
    {
      "downloads": 10329,
      "day": "2024-08-04"
    },
    {
      "downloads": 45799,
      "day": "2024-08-05"
    },
    {
      "downloads": 47333,
      "day": "2024-08-06"
    },
    {
      "downloads": 48939,
      "day": "2024-08-07"
    },
    {
      "downloads": 50131,
      "day": "2024-08-08"
    },
    {
      "downloads": 43682,
      "day": "2024-08-09"
    },
    {
      "downloads": 11234,
      "day": "2024-08-10"
    },
    {
      "downloads": 10424,
      "day": "2024-08-11"
    },
    {
      "downloads": 47804,
      "day": "2024-08-12"
    },
    {
      "downloads": 49502,
      "day": "2024-08-13"
    },
    {
      "downloads": 48613,
      "day": "2024-08-14"
    },
    {
      "downloads": 36903,
      "day": "2024-08-15"
    },
    {
      "downloads": 42990,
      "day": "2024-08-16"
    },
    {
      "downloads": 9441,
      "day": "2024-08-17"
    },
    {
      "downloads": 9670,
      "day": "2024-08-18"
    },
    {
      "downloads": 46858,
      "day": "2024-08-19"
    },
    {
      "downloads": 50551,
      "day": "2024-08-20"
    },
    {
      "downloads": 45238,
      "day": "2024-08-21"
    },
    {
      "downloads": 51636,
      "day": "2024-08-22"
    },
    {
      "downloads": 41655,
      "day": "2024-08-23"
    },
    {
      "downloads": 10755,
      "day": "2024-08-24"
    },
    {
      "downloads": 10837,
      "day": "2024-08-25"
    },
    {
      "downloads": 48635,
      "day": "2024-08-26"
    },
    {
      "downloads": 54797,
      "day": "2024-08-27"
    },
    {
      "downloads": 54097,
      "day": "2024-08-28"
    },
    {
      "downloads": 55625,
      "day": "2024-08-29"
    },
    {
      "downloads": 43606,
      "day": "2024-08-30"
    },
    {
      "downloads": 11379,
      "day": "2024-08-31"
    },
    {
      "downloads": 12523,
      "day": "2024-09-01"
    },
    {
      "downloads": 41079,
      "day": "2024-09-02"
    },
    {
      "downloads": 51781,
      "day": "2024-09-03"
    },
    {
      "downloads": 50610,
      "day": "2024-09-04"
    },
    {
      "downloads": 58127,
      "day": "2024-09-05"
    },
    {
      "downloads": 47152,
      "day": "2024-09-06"
    },
    {
      "downloads": 14599,
      "day": "2024-09-07"
    },
    {
      "downloads": 13126,
      "day": "2024-09-08"
    },
    {
      "downloads": 53163,
      "day": "2024-09-09"
    },
    {
      "downloads": 53836,
      "day": "2024-09-10"
    },
    {
      "downloads": 50568,
      "day": "2024-09-11"
    },
    {
      "downloads": 52086,
      "day": "2024-09-12"
    },
    {
      "downloads": 48028,
      "day": "2024-09-13"
    },
    {
      "downloads": 11177,
      "day": "2024-09-14"
    },
    {
      "downloads": 11816,
      "day": "2024-09-15"
    },
    {
      "downloads": 51705,
      "day": "2024-09-16"
    },
    {
      "downloads": 49866,
      "day": "2024-09-17"
    },
    {
      "downloads": 49716,
      "day": "2024-09-18"
    },
    {
      "downloads": 52041,
      "day": "2024-09-19"
    },
    {
      "downloads": 43774,
      "day": "2024-09-20"
    },
    {
      "downloads": 10890,
      "day": "2024-09-21"
    },
    {
      "downloads": 11077,
      "day": "2024-09-22"
    },
    {
      "downloads": 52056,
      "day": "2024-09-23"
    },
    {
      "downloads": 52089,
      "day": "2024-09-24"
    },
    {
      "downloads": 53725,
      "day": "2024-09-25"
    },
    {
      "downloads": 54632,
      "day": "2024-09-26"
    },
    {
      "downloads": 47010,
      "day": "2024-09-27"
    },
    {
      "downloads": 12618,
      "day": "2024-09-28"
    },
    {
      "downloads": 12172,
      "day": "2024-09-29"
    },
    {
      "downloads": 54704,
      "day": "2024-09-30"
    },
    {
      "downloads": 49903,
      "day": "2024-10-01"
    },
    {
      "downloads": 50959,
      "day": "2024-10-02"
    },
    {
      "downloads": 46057,
      "day": "2024-10-03"
    },
    {
      "downloads": 39390,
      "day": "2024-10-04"
    },
    {
      "downloads": 11004,
      "day": "2024-10-05"
    },
    {
      "downloads": 11982,
      "day": "2024-10-06"
    },
    {
      "downloads": 46219,
      "day": "2024-10-07"
    },
    {
      "downloads": 48568,
      "day": "2024-10-08"
    },
    {
      "downloads": 44357,
      "day": "2024-10-09"
    },
    {
      "downloads": 46653,
      "day": "2024-10-10"
    },
    {
      "downloads": 36958,
      "day": "2024-10-11"
    },
    {
      "downloads": 11716,
      "day": "2024-10-12"
    },
    {
      "downloads": 11971,
      "day": "2024-10-13"
    },
    {
      "downloads": 47863,
      "day": "2024-10-14"
    },
    {
      "downloads": 51881,
      "day": "2024-10-15"
    },
    {
      "downloads": 53132,
      "day": "2024-10-16"
    },
    {
      "downloads": 54151,
      "day": "2024-10-17"
    },
    {
      "downloads": 42493,
      "day": "2024-10-18"
    },
    {
      "downloads": 11868,
      "day": "2024-10-19"
    },
    {
      "downloads": 12898,
      "day": "2024-10-20"
    },
    {
      "downloads": 52629,
      "day": "2024-10-21"
    },
    {
      "downloads": 51058,
      "day": "2024-10-22"
    },
    {
      "downloads": 49633,
      "day": "2024-10-23"
    },
    {
      "downloads": 44931,
      "day": "2024-10-24"
    },
    {
      "downloads": 40331,
      "day": "2024-10-25"
    },
    {
      "downloads": 13737,
      "day": "2024-10-26"
    },
    {
      "downloads": 12541,
      "day": "2024-10-27"
    },
    {
      "downloads": 48369,
      "day": "2024-10-28"
    },
    {
      "downloads": 48414,
      "day": "2024-10-29"
    },
    {
      "downloads": 46532,
      "day": "2024-10-30"
    },
    {
      "downloads": 41008,
      "day": "2024-10-31"
    },
    {
      "downloads": 33109,
      "day": "2024-11-01"
    },
    {
      "downloads": 10825,
      "day": "2024-11-02"
    }
  ]
}