{
  "start": "2023-11-05",
  "end": "2024-11-03",
  "package": "p-pipe",
  "downloads": [
    {
      "downloads": 98104,
      "day": "2023-11-05"
    },
    {
      "downloads": 413273,
      "day": "2023-11-06"
    },
    {
      "downloads": 448013,
      "day": "2023-11-07"
    },
    {
      "downloads": 445338,
      "day": "2023-11-08"
    },
    {
      "downloads": 420617,
      "day": "2023-11-09"
    },
    {
      "downloads": 338486,
      "day": "2023-11-10"
    },
    {
      "downloads": 96239,
      "day": "2023-11-11"
    },
    {
      "downloads": 105458,
      "day": "2023-11-12"
    },
    {
      "downloads": 406528,
      "day": "2023-11-13"
    },
    {
      "downloads": 432391,
      "day": "2023-11-14"
    },
    {
      "downloads": 422488,
      "day": "2023-11-15"
    },
    {
      "downloads": 432010,
      "day": "2023-11-16"
    },
    {
      "downloads": 355483,
      "day": "2023-11-17"
    },
    {
      "downloads": 88816,
      "day": "2023-11-18"
    },
    {
      "downloads": 108348,
      "day": "2023-11-19"
    },
    {
      "downloads": 405709,
      "day": "2023-11-20"
    },
    {
      "downloads": 430194,
      "day": "2023-11-21"
    },
    {
      "downloads": 411672,
      "day": "2023-11-22"
    },
    {
      "downloads": 347484,
      "day": "2023-11-23"
    },
    {
      "downloads": 282001,
      "day": "2023-11-24"
    },
    {
      "downloads": 80712,
      "day": "2023-11-25"
    },
    {
      "downloads": 109717,
      "day": "2023-11-26"
    },
    {
      "downloads": 412728,
      "day": "2023-11-27"
    },
    {
      "downloads": 431391,
      "day": "2023-11-28"
    },
    {
      "downloads": 429240,
      "day": "2023-11-29"
    },
    {
      "downloads": 437930,
      "day": "2023-11-30"
    },
    {
      "downloads": 352878,
      "day": "2023-12-01"
    },
    {
      "downloads": 92794,
      "day": "2023-12-02"
    },
    {
      "downloads": 122282,
      "day": "2023-12-03"
    },
    {
      "downloads": 439743,
      "day": "2023-12-04"
    },
    {
      "downloads": 443807,
      "day": "2023-12-05"
    },
    {
      "downloads": 414181,
      "day": "2023-12-06"
    },
    {
      "downloads": 416994,
      "day": "2023-12-07"
    },
    {
      "downloads": 327835,
      "day": "2023-12-08"
    },
    {
      "downloads": 87885,
      "day": "2023-12-09"
    },
    {
      "downloads": 104727,
      "day": "2023-12-10"
    },
    {
      "downloads": 398480,
      "day": "2023-12-11"
    },
    {
      "downloads": 414913,
      "day": "2023-12-12"
    },
    {
      "downloads": 413790,
      "day": "2023-12-13"
    },
    {
      "downloads": 390245,
      "day": "2023-12-14"
    },
    {
      "downloads": 327446,
      "day": "2023-12-15"
    },
    {
      "downloads": 82458,
      "day": "2023-12-16"
    },
    {
      "downloads": 83219,
      "day": "2023-12-17"
    },
    {
      "downloads": 374642,
      "day": "2023-12-18"
    },
    {
      "downloads": 389225,
      "day": "2023-12-19"
    },
    {
      "downloads": 372931,
      "day": "2023-12-20"
    },
    {
      "downloads": 334446,
      "day": "2023-12-21"
    },
    {
      "downloads": 245256,
      "day": "2023-12-22"
    },
    {
      "downloads": 69616,
      "day": "2023-12-23"
    },
    {
      "downloads": 69654,
      "day": "2023-12-24"
    },
    {
      "downloads": 114063,
      "day": "2023-12-25"
    },
    {
      "downloads": 160916,
      "day": "2023-12-26"
    },
    {
      "downloads": 206433,
      "day": "2023-12-27"
    },
    {
      "downloads": 200709,
      "day": "2023-12-28"
    },
    {
      "downloads": 163429,
      "day": "2023-12-29"
    },
    {
      "downloads": 72444,
      "day": "2023-12-30"
    },
    {
      "downloads": 68317,
      "day": "2023-12-31"
    },
    {
      "downloads": 100544,
      "day": "2024-01-01"
    },
    {
      "downloads": 275242,
      "day": "2024-01-02"
    },
    {
      "downloads": 322972,
      "day": "2024-01-03"
    },
    {
      "downloads": 336547,
      "day": "2024-01-04"
    },
    {
      "downloads": 301582,
      "day": "2024-01-05"
    },
    {
      "downloads": 80605,
      "day": "2024-01-06"
    },
    {
      "downloads": 81003,
      "day": "2024-01-07"
    },
    {
      "downloads": 367312,
      "day": "2024-01-08"
    },
    {
      "downloads": 397397,
      "day": "2024-01-09"
    },
    {
      "downloads": 408659,
      "day": "2024-01-10"
    },
    {
      "downloads": 403073,
      "day": "2024-01-11"
    },
    {
      "downloads": 346039,
      "day": "2024-01-12"
    },
    {
      "downloads": 83443,
      "day": "2024-01-13"
    },
    {
      "downloads": 84977,
      "day": "2024-01-14"
    },
    {
      "downloads": 342473,
      "day": "2024-01-15"
    },
    {
      "downloads": 396130,
      "day": "2024-01-16"
    },
    {
      "downloads": 413728,
      "day": "2024-01-17"
    },
    {
      "downloads": 400780,
      "day": "2024-01-18"
    },
    {
      "downloads": 354264,
      "day": "2024-01-19"
    },
    {
      "downloads": 88937,
      "day": "2024-01-20"
    },
    {
      "downloads": 87209,
      "day": "2024-01-21"
    },
    {
      "downloads": 409194,
      "day": "2024-01-22"
    },
    {
      "downloads": 417429,
      "day": "2024-01-23"
    },
    {
      "downloads": 405820,
      "day": "2024-01-24"
    },
    {
      "downloads": 398555,
      "day": "2024-01-25"
    },
    {
      "downloads": 323846,
      "day": "2024-01-26"
    },
    {
      "downloads": 84354,
      "day": "2024-01-27"
    },
    {
      "downloads": 84580,
      "day": "2024-01-28"
    },
    {
      "downloads": 401375,
      "day": "2024-01-29"
    },
    {
      "downloads": 419526,
      "day": "2024-01-30"
    },
    {
      "downloads": 416585,
      "day": "2024-01-31"
    },
    {
      "downloads": 410088,
      "day": "2024-02-01"
    },
    {
      "downloads": 351826,
      "day": "2024-02-02"
    },
    {
      "downloads": 83010,
      "day": "2024-02-03"
    },
    {
      "downloads": 88010,
      "day": "2024-02-04"
    },
    {
      "downloads": 401788,
      "day": "2024-02-05"
    },
    {
      "downloads": 427241,
      "day": "2024-02-06"
    },
    {
      "downloads": 411873,
      "day": "2024-02-07"
    },
    {
      "downloads": 392634,
      "day": "2024-02-08"
    },
    {
      "downloads": 340299,
      "day": "2024-02-09"
    },
    {
      "downloads": 84959,
      "day": "2024-02-10"
    },
    {
      "downloads": 87003,
      "day": "2024-02-11"
    },
    {
      "downloads": 354455,
      "day": "2024-02-12"
    },
    {
      "downloads": 388238,
      "day": "2024-02-13"
    },
    {
      "downloads": 388403,
      "day": "2024-02-14"
    },
    {
      "downloads": 394347,
      "day": "2024-02-15"
    },
    {
      "downloads": 345157,
      "day": "2024-02-16"
    },
    {
      "downloads": 82335,
      "day": "2024-02-17"
    },
    {
      "downloads": 84771,
      "day": "2024-02-18"
    },
    {
      "downloads": 348382,
      "day": "2024-02-19"
    },
    {
      "downloads": 412823,
      "day": "2024-02-20"
    },
    {
      "downloads": 418579,
      "day": "2024-02-21"
    },
    {
      "downloads": 400091,
      "day": "2024-02-22"
    },
    {
      "downloads": 344201,
      "day": "2024-02-23"
    },
    {
      "downloads": 85525,
      "day": "2024-02-24"
    },
    {
      "downloads": 88990,
      "day": "2024-02-25"
    },
    {
      "downloads": 409993,
      "day": "2024-02-26"
    },
    {
      "downloads": 425180,
      "day": "2024-02-27"
    },
    {
      "downloads": 417628,
      "day": "2024-02-28"
    },
    {
      "downloads": 420678,
      "day": "2024-02-29"
    },
    {
      "downloads": 360509,
      "day": "2024-03-01"
    },
    {
      "downloads": 92254,
      "day": "2024-03-02"
    },
    {
      "downloads": 90562,
      "day": "2024-03-03"
    },
    {
      "downloads": 416920,
      "day": "2024-03-04"
    },
    {
      "downloads": 428469,
      "day": "2024-03-05"
    },
    {
      "downloads": 423769,
      "day": "2024-03-06"
    },
    {
      "downloads": 426335,
      "day": "2024-03-07"
    },
    {
      "downloads": 330031,
      "day": "2024-03-08"
    },
    {
      "downloads": 93143,
      "day": "2024-03-09"
    },
    {
      "downloads": 90798,
      "day": "2024-03-10"
    },
    {
      "downloads": 407433,
      "day": "2024-03-11"
    },
    {
      "downloads": 416655,
      "day": "2024-03-12"
    },
    {
      "downloads": 415755,
      "day": "2024-03-13"
    },
    {
      "downloads": 400153,
      "day": "2024-03-14"
    },
    {
      "downloads": 354630,
      "day": "2024-03-15"
    },
    {
      "downloads": 97400,
      "day": "2024-03-16"
    },
    {
      "downloads": 94291,
      "day": "2024-03-17"
    },
    {
      "downloads": 405797,
      "day": "2024-03-18"
    },
    {
      "downloads": 416888,
      "day": "2024-03-19"
    },
    {
      "downloads": 408197,
      "day": "2024-03-20"
    },
    {
      "downloads": 416410,
      "day": "2024-03-21"
    },
    {
      "downloads": 345307,
      "day": "2024-03-22"
    },
    {
      "downloads": 88706,
      "day": "2024-03-23"
    },
    {
      "downloads": 88209,
      "day": "2024-03-24"
    },
    {
      "downloads": 401681,
      "day": "2024-03-25"
    },
    {
      "downloads": 308427,
      "day": "2024-03-26"
    },
    {
      "downloads": 415312,
      "day": "2024-03-27"
    },
    {
      "downloads": 373625,
      "day": "2024-03-28"
    },
    {
      "downloads": 236682,
      "day": "2024-03-29"
    },
    {
      "downloads": 78905,
      "day": "2024-03-30"
    },
    {
      "downloads": 80518,
      "day": "2024-03-31"
    },
    {
      "downloads": 275561,
      "day": "2024-04-01"
    },
    {
      "downloads": 394059,
      "day": "2024-04-02"
    },
    {
      "downloads": 406423,
      "day": "2024-04-03"
    },
    {
      "downloads": 389783,
      "day": "2024-04-04"
    },
    {
      "downloads": 331651,
      "day": "2024-04-05"
    },
    {
      "downloads": 90669,
      "day": "2024-04-06"
    },
    {
      "downloads": 88183,
      "day": "2024-04-07"
    },
    {
      "downloads": 376464,
      "day": "2024-04-08"
    },
    {
      "downloads": 384309,
      "day": "2024-04-09"
    },
    {
      "downloads": 379832,
      "day": "2024-04-10"
    },
    {
      "downloads": 377306,
      "day": "2024-04-11"
    },
    {
      "downloads": 333224,
      "day": "2024-04-12"
    },
    {
      "downloads": 84188,
      "day": "2024-04-13"
    },
    {
      "downloads": 81845,
      "day": "2024-04-14"
    },
    {
      "downloads": 396521,
      "day": "2024-04-15"
    },
    {
      "downloads": 397247,
      "day": "2024-04-16"
    },
    {
      "downloads": 392252,
      "day": "2024-04-17"
    },
    {
      "downloads": 397714,
      "day": "2024-04-18"
    },
    {
      "downloads": 350344,
      "day": "2024-04-19"
    },
    {
      "downloads": 101778,
      "day": "2024-04-20"
    },
    {
      "downloads": 93064,
      "day": "2024-04-21"
    },
    {
      "downloads": 393489,
      "day": "2024-04-22"
    },
    {
      "downloads": 405987,
      "day": "2024-04-23"
    },
    {
      "downloads": 398329,
      "day": "2024-04-24"
    },
    {
      "downloads": 383427,
      "day": "2024-04-25"
    },
    {
      "downloads": 329138,
      "day": "2024-04-26"
    },
    {
      "downloads": 84336,
      "day": "2024-04-27"
    },
    {
      "downloads": 80492,
      "day": "2024-04-28"
    },
    {
      "downloads": 367924,
      "day": "2024-04-29"
    },
    {
      "downloads": 386426,
      "day": "2024-04-30"
    },
    {
      "downloads": 260542,
      "day": "2024-05-01"
    },
    {
      "downloads": 376044,
      "day": "2024-05-02"
    },
    {
      "downloads": 313965,
      "day": "2024-05-03"
    },
    {
      "downloads": 78116,
      "day": "2024-05-04"
    },
    {
      "downloads": 81964,
      "day": "2024-05-05"
    },
    {
      "downloads": 348338,
      "day": "2024-05-06"
    },
    {
      "downloads": 396210,
      "day": "2024-05-07"
    },
    {
      "downloads": 362545,
      "day": "2024-05-08"
    },
    {
      "downloads": 328405,
      "day": "2024-05-09"
    },
    {
      "downloads": 312085,
      "day": "2024-05-10"
    },
    {
      "downloads": 79540,
      "day": "2024-05-11"
    },
    {
      "downloads": 78922,
      "day": "2024-05-12"
    },
    {
      "downloads": 391685,
      "day": "2024-05-13"
    },
    {
      "downloads": 401015,
      "day": "2024-05-14"
    },
    {
      "downloads": 399917,
      "day": "2024-05-15"
    },
    {
      "downloads": 406985,
      "day": "2024-05-16"
    },
    {
      "downloads": 337465,
      "day": "2024-05-17"
    },
    {
      "downloads": 77568,
      "day": "2024-05-18"
    },
    {
      "downloads": 79504,
      "day": "2024-05-19"
    },
    {
      "downloads": 329737,
      "day": "2024-05-20"
    },
    {
      "downloads": 386317,
      "day": "2024-05-21"
    },
    {
      "downloads": 395067,
      "day": "2024-05-22"
    },
    {
      "downloads": 394670,
      "day": "2024-05-23"
    },
    {
      "downloads": 327588,
      "day": "2024-05-24"
    },
    {
      "downloads": 72151,
      "day": "2024-05-25"
    },
    {
      "downloads": 79727,
      "day": "2024-05-26"
    },
    {
      "downloads": 314444,
      "day": "2024-05-27"
    },
    {
      "downloads": 385713,
      "day": "2024-05-28"
    },
    {
      "downloads": 390447,
      "day": "2024-05-29"
    },
    {
      "downloads": 357543,
      "day": "2024-05-30"
    },
    {
      "downloads": 321464,
      "day": "2024-05-31"
    },
    {
      "downloads": 89439,
      "day": "2024-06-01"
    },
    {
      "downloads": 86812,
      "day": "2024-06-02"
    },
    {
      "downloads": 391858,
      "day": "2024-06-03"
    },
    {
      "downloads": 400291,
      "day": "2024-06-04"
    },
    {
      "downloads": 406807,
      "day": "2024-06-05"
    },
    {
      "downloads": 388166,
      "day": "2024-06-06"
    },
    {
      "downloads": 314492,
      "day": "2024-06-07"
    },
    {
      "downloads": 75912,
      "day": "2024-06-08"
    },
    {
      "downloads": 81227,
      "day": "2024-06-09"
    },
    {
      "downloads": 374062,
      "day": "2024-06-10"
    },
    {
      "downloads": 397604,
      "day": "2024-06-11"
    },
    {
      "downloads": 390491,
      "day": "2024-06-12"
    },
    {
      "downloads": 387234,
      "day": "2024-06-13"
    },
    {
      "downloads": 330567,
      "day": "2024-06-14"
    },
    {
      "downloads": 85575,
      "day": "2024-06-15"
    },
    {
      "downloads": 92553,
      "day": "2024-06-16"
    },
    {
      "downloads": 361044,
      "day": "2024-06-17"
    },
    {
      "downloads": 390279,
      "day": "2024-06-18"
    },
    {
      "downloads": 378409,
      "day": "2024-06-19"
    },
    {
      "downloads": 385727,
      "day": "2024-06-20"
    },
    {
      "downloads": 326185,
      "day": "2024-06-21"
    },
    {
      "downloads": 78888,
      "day": "2024-06-22"
    },
    {
      "downloads": 80719,
      "day": "2024-06-23"
    },
    {
      "downloads": 379772,
      "day": "2024-06-24"
    },
    {
      "downloads": 394261,
      "day": "2024-06-25"
    },
    {
      "downloads": 388269,
      "day": "2024-06-26"
    },
    {
      "downloads": 388169,
      "day": "2024-06-27"
    },
    {
      "downloads": 309959,
      "day": "2024-06-28"
    },
    {
      "downloads": 76810,
      "day": "2024-06-29"
    },
    {
      "downloads": 105582,
      "day": "2024-06-30"
    },
    {
      "downloads": 392447,
      "day": "2024-07-01"
    },
    {
      "downloads": 421078,
      "day": "2024-07-02"
    },
    {
      "downloads": 412896,
      "day": "2024-07-03"
    },
    {
      "downloads": 335346,
      "day": "2024-07-04"
    },
    {
      "downloads": 275123,
      "day": "2024-07-05"
    },
    {
      "downloads": 71164,
      "day": "2024-07-06"
    },
    {
      "downloads": 74784,
      "day": "2024-07-07"
    },
    {
      "downloads": 381325,
      "day": "2024-07-08"
    },
    {
      "downloads": 388011,
      "day": "2024-07-09"
    },
    {
      "downloads": 389043,
      "day": "2024-07-10"
    },
    {
      "downloads": 393755,
      "day": "2024-07-11"
    },
    {
      "downloads": 324400,
      "day": "2024-07-12"
    },
    {
      "downloads": 91935,
      "day": "2024-07-13"
    },
    {
      "downloads": 91922,
      "day": "2024-07-14"
    },
    {
      "downloads": 376628,
      "day": "2024-07-15"
    },
    {
      "downloads": 403854,
      "day": "2024-07-16"
    },
    {
      "downloads": 402908,
      "day": "2024-07-17"
    },
    {
      "downloads": 391679,
      "day": "2024-07-18"
    },
    {
      "downloads": 324123,
      "day": "2024-07-19"
    },
    {
      "downloads": 90244,
      "day": "2024-07-20"
    },
    {
      "downloads": 91900,
      "day": "2024-07-21"
    },
    {
      "downloads": 384253,
      "day": "2024-07-22"
    },
    {
      "downloads": 404080,
      "day": "2024-07-23"
    },
    {
      "downloads": 390097,
      "day": "2024-07-24"
    },
    {
      "downloads": 390166,
      "day": "2024-07-25"
    },
    {
      "downloads": 316202,
      "day": "2024-07-26"
    },
    {
      "downloads": 75606,
      "day": "2024-07-27"
    },
    {
      "downloads": 76905,
      "day": "2024-07-28"
    },
    {
      "downloads": 395786,
      "day": "2024-07-29"
    },
    {
      "downloads": 385443,
      "day": "2024-07-30"
    },
    {
      "downloads": 371202,
      "day": "2024-07-31"
    },
    {
      "downloads": 383706,
      "day": "2024-08-01"
    },
    {
      "downloads": 325999,
      "day": "2024-08-02"
    },
    {
      "downloads": 78337,
      "day": "2024-08-03"
    },
    {
      "downloads": 80963,
      "day": "2024-08-04"
    },
    {
      "downloads": 366159,
      "day": "2024-08-05"
    },
    {
      "downloads": 400829,
      "day": "2024-08-06"
    },
    {
      "downloads": 392539,
      "day": "2024-08-07"
    },
    {
      "downloads": 395464,
      "day": "2024-08-08"
    },
    {
      "downloads": 331222,
      "day": "2024-08-09"
    },
    {
      "downloads": 81718,
      "day": "2024-08-10"
    },
    {
      "downloads": 86709,
      "day": "2024-08-11"
    },
    {
      "downloads": 362869,
      "day": "2024-08-12"
    },
    {
      "downloads": 386591,
      "day": "2024-08-13"
    },
    {
      "downloads": 384648,
      "day": "2024-08-14"
    },
    {
      "downloads": 296942,
      "day": "2024-08-15"
    },
    {
      "downloads": 292114,
      "day": "2024-08-16"
    },
    {
      "downloads": 75680,
      "day": "2024-08-17"
    },
    {
      "downloads": 83840,
      "day": "2024-08-18"
    },
    {
      "downloads": 359305,
      "day": "2024-08-19"
    },
    {
      "downloads": 394738,
      "day": "2024-08-20"
    },
    {
      "downloads": 365803,
      "day": "2024-08-21"
    },
    {
      "downloads": 372814,
      "day": "2024-08-22"
    },
    {
      "downloads": 320569,
      "day": "2024-08-23"
    },
    {
      "downloads": 78729,
      "day": "2024-08-24"
    },
    {
      "downloads": 86783,
      "day": "2024-08-25"
    },
    {
      "downloads": 370299,
      "day": "2024-08-26"
    },
    {
      "downloads": 400921,
      "day": "2024-08-27"
    },
    {
      "downloads": 409686,
      "day": "2024-08-28"
    },
    {
      "downloads": 403103,
      "day": "2024-08-29"
    },
    {
      "downloads": 324662,
      "day": "2024-08-30"
    },
    {
      "downloads": 87942,
      "day": "2024-08-31"
    },
    {
      "downloads": 100192,
      "day": "2024-09-01"
    },
    {
      "downloads": 331352,
      "day": "2024-09-02"
    },
    {
      "downloads": 390116,
      "day": "2024-09-03"
    },
    {
      "downloads": 411396,
      "day": "2024-09-04"
    },
    {
      "downloads": 397883,
      "day": "2024-09-05"
    },
    {
      "downloads": 328114,
      "day": "2024-09-06"
    },
    {
      "downloads": 80480,
      "day": "2024-09-07"
    },
    {
      "downloads": 89254,
      "day": "2024-09-08"
    },
    {
      "downloads": 394928,
      "day": "2024-09-09"
    },
    {
      "downloads": 402582,
      "day": "2024-09-10"
    },
    {
      "downloads": 421213,
      "day": "2024-09-11"
    },
    {
      "downloads": 422562,
      "day": "2024-09-12"
    },
    {
      "downloads": 341333,
      "day": "2024-09-13"
    },
    {
      "downloads": 84626,
      "day": "2024-09-14"
    },
    {
      "downloads": 84863,
      "day": "2024-09-15"
    },
    {
      "downloads": 378594,
      "day": "2024-09-16"
    },
    {
      "downloads": 396104,
      "day": "2024-09-17"
    },
    {
      "downloads": 396858,
      "day": "2024-09-18"
    },
    {
      "downloads": 383994,
      "day": "2024-09-19"
    },
    {
      "downloads": 331069,
      "day": "2024-09-20"
    },
    {
      "downloads": 88109,
      "day": "2024-09-21"
    },
    {
      "downloads": 90392,
      "day": "2024-09-22"
    },
    {
      "downloads": 388682,
      "day": "2024-09-23"
    },
    {
      "downloads": 415284,
      "day": "2024-09-24"
    },
    {
      "downloads": 415404,
      "day": "2024-09-25"
    },
    {
      "downloads": 404212,
      "day": "2024-09-26"
    },
    {
      "downloads": 322934,
      "day": "2024-09-27"
    },
    {
      "downloads": 88531,
      "day": "2024-09-28"
    },
    {
      "downloads": 96594,
      "day": "2024-09-29"
    },
    {
      "downloads": 375157,
      "day": "2024-09-30"
    },
    {
      "downloads": 382286,
      "day": "2024-10-01"
    },
    {
      "downloads": 351528,
      "day": "2024-10-02"
    },
    {
      "downloads": 356828,
      "day": "2024-10-03"
    },
    {
      "downloads": 320186,
      "day": "2024-10-04"
    },
    {
      "downloads": 81747,
      "day": "2024-10-05"
    },
    {
      "downloads": 90813,
      "day": "2024-10-06"
    },
    {
      "downloads": 382025,
      "day": "2024-10-07"
    },
    {
      "downloads": 389206,
      "day": "2024-10-08"
    },
    {
      "downloads": 391172,
      "day": "2024-10-09"
    },
    {
      "downloads": 383983,
      "day": "2024-10-10"
    },
    {
      "downloads": 312757,
      "day": "2024-10-11"
    },
    {
      "downloads": 83008,
      "day": "2024-10-12"
    },
    {
      "downloads": 91810,
      "day": "2024-10-13"
    },
    {
      "downloads": 345936,
      "day": "2024-10-14"
    },
    {
      "downloads": 398216,
      "day": "2024-10-15"
    },
    {
      "downloads": 383397,
      "day": "2024-10-16"
    },
    {
      "downloads": 380617,
      "day": "2024-10-17"
    },
    {
      "downloads": 327647,
      "day": "2024-10-18"
    },
    {
      "downloads": 91795,
      "day": "2024-10-19"
    },
    {
      "downloads": 97764,
      "day": "2024-10-20"
    },
    {
      "downloads": 383795,
      "day": "2024-10-21"
    },
    {
      "downloads": 402125,
      "day": "2024-10-22"
    },
    {
      "downloads": 401175,
      "day": "2024-10-23"
    },
    {
      "downloads": 387772,
      "day": "2024-10-24"
    },
    {
      "downloads": 349989,
      "day": "2024-10-25"
    },
    {
      "downloads": 94634,
      "day": "2024-10-26"
    },
    {
      "downloads": 106583,
      "day": "2024-10-27"
    },
    {
      "downloads": 374024,
      "day": "2024-10-28"
    },
    {
      "downloads": 408754,
      "day": "2024-10-29"
    },
    {
      "downloads": 385725,
      "day": "2024-10-30"
    },
    {
      "downloads": 350779,
      "day": "2024-10-31"
    },
    {
      "downloads": 289908,
      "day": "2024-11-01"
    },
    {
      "downloads": 96812,
      "day": "2024-11-02"
    },
    {
      "downloads": 99950,
      "day": "2024-11-03"
    }
  ]
}